{
  "Mode": [
    {
      "id": "kg_Mode_0006",
      "name": "NO_NAME",
      "missing_fields": [
        "class",
        "name"
      ]
    },
    {
      "id": "kg_Mode_0008",
      "name": null,
      "missing_fields": [
        "name",
        "usage",
        "scenarios"
      ]
    },
    {
      "id": "kg_Mode_0011",
      "name": "worst",
      "missing_fields": [
        "usage",
        "scenarios"
      ]
    },
    {
      "id": "kg_Mode_0015",
      "name": "test_fast",
      "missing_fields": [
        "usage",
        "scenarios"
      ]
    },
    {
      "id": "kg_Mode_0016",
      "name": "test_slow",
      "missing_fields": [
        "usage",
        "scenarios"
      ]
    },
    {
      "id": "kg_Mode_0023",
      "name": "NO_NAME",
      "missing_fields": [
        "class",
        "name"
      ]
    },
    {
      "id": "kg_Mode_0027",
      "name": "NO_NAME",
      "missing_fields": [
        "class",
        "name",
        "usage"
      ]
    },
    {
      "id": "kg_Mode_0029",
      "name": "NO_NAME",
      "missing_fields": [
        "class",
        "name"
      ]
    },
    {
      "id": "kg_Mode_0030",
      "name": null,
      "missing_fields": [
        "name",
        "usage",
        "scenarios"
      ]
    },
    {
      "id": "kg_Mode_0032",
      "name": "NO_NAME",
      "missing_fields": [
        "class",
        "name"
      ]
    }
  ],
  "Example": [
    {
      "id": "kg_Example_0002",
      "name": "set_parameter eco_cell_classify_rule {cell_attribute}  ;# set the cell classify rule for gate sizing: cell_attribute, nominal_keywords, and nominal_regex.",
      "missing_fields": [
        "scenarios"
      ]
    },
    {
      "id": "kg_Example_0003",
      "name": "set_parameter eco_cell_match_attribute {footprint} ;# set the size cell attribute matching type: footprint, user_function_class, pin_function.",
      "missing_fields": [
        "scenarios"
      ]
    },
    {
      "id": "kg_Example_0004",
      "name": "set_parameter eco_cell_nominal_swap_keywords {lvt@l30 lvt@l40 svt@l30 svt@l40 hvt@l30 hvt@l40}  ;# set the nominal keywords for swapping cells.",
      "missing_fields": [
        "scenarios"
      ]
    },
    {
      "id": "kg_Example_0008",
      "name": "write_design_changes -format ICC -eco_file_prefix xtop_opt_icc -output_dir $eco_output_dir",
      "missing_fields": [
        "scenarios"
      ]
    },
    {
      "id": "kg_Example_0009",
      "name": "write_design_changes -format PT -eco_file_prefix xtop_opt_pt -output_dir $eco_output_dir",
      "missing_fields": [
        "usage",
        "scenarios"
      ]
    },
    {
      "id": "kg_Example_0013",
      "name": "xtop > set_parameter eco_post_mask_mode true",
      "missing_fields": [
        "usage",
        "scenarios"
      ]
    },
    {
      "id": "kg_Example_0014",
      "name": "set_parameter eco_post_mask_mode true",
      "missing_fields": [
        "usage",
        "scenarios"
      ]
    },
    {
      "id": "kg_Example_0016",
      "name": "NO_NAME",
      "missing_fields": [
        "class",
        "name",
        "usage"
      ]
    },
    {
      "id": "kg_Example_0017",
      "name": "xtop> get_paths -help",
      "missing_fields": [
        "scenarios"
      ]
    },
    {
      "id": "kg_Example_0018",
      "name": "xtop> commit_clock_eco -hold -top 10",
      "missing_fields": [
        "scenarios"
      ]
    },
    {
      "id": "kg_Example_0019",
      "name": "xtop> fix_violations_by_clock_eco -buffer CKBUFF1 -setup -trace_level 4",
      "missing_fields": [
        "scenarios"
      ]
    },
    {
      "id": "kg_Example_0035",
      "name": "stop_gui",
      "missing_fields": [
        "usage",
        "scenarios"
      ]
    },
    {
      "id": "kg_Example_0040",
      "name": "NO_NAME",
      "missing_fields": [
        "class",
        "name",
        "usage"
      ]
    },
    {
      "id": "kg_Example_0041",
      "name": "% current_instance top/sub/sub_sub",
      "missing_fields": [
        "scenarios"
      ]
    },
    {
      "id": "kg_Example_0042",
      "name": "NO_NAME",
      "missing_fields": [
        "class",
        "name"
      ]
    },
    {
      "id": "kg_Example_0044",
      "name": "NO_NAME",
      "missing_fields": [
        "class",
        "name"
      ]
    },
    {
      "id": "kg_Example_0045",
      "name": "% get_lib_pins */* -filter \"is_preset_pin==true\"",
      "missing_fields": [
        "scenarios"
      ]
    },
    {
      "id": "kg_Example_0046",
      "name": "% get_nets -filter \"total_capacitance_max > 0.03\" \"n81\", \"n82\", \"n83\"",
      "missing_fields": [
        "scenarios"
      ]
    },
    {
      "id": "kg_Example_0047",
      "name": "% read_aocv -scenario func_setup { setup_func.aocvm}",
      "missing_fields": [
        "scenarios"
      ]
    },
    {
      "id": "kg_Example_0050",
      "name": "NO_NAME",
      "missing_fields": [
        "class",
        "name"
      ]
    },
    {
      "id": "kg_Example_0051",
      "name": "NO_NAME",
      "missing_fields": [
        "class",
        "name"
      ]
    },
    {
      "id": "kg_Example_0052",
      "name": "% set_rail_voltage -min -rail_value 0.92 [get_cells I_PCS3]",
      "missing_fields": [
        "scenarios"
      ]
    },
    {
      "id": "kg_Example_0055",
      "name": "% close_workspace",
      "missing_fields": [
        "scenarios"
      ]
    },
    {
      "id": "kg_Example_0056",
      "name": "84",
      "missing_fields": [
        "usage",
        "scenarios"
      ]
    },
    {
      "id": "kg_Example_0057",
      "name": "% create_design_definition -name sub   \\\n    -verilogs {/home/user/date/sub.v}  \\\n    -def {/home/user/date/sub.def}\n% configure_design_definition -name sub -new_name sub1 \\\n    -verilogs {/home/user/date/sub1.v} \\\n    -def {/home/user/date/sub1.def}",
      "missing_fields": [
        "scenarios"
      ]
    },
    {
      "id": "kg_Example_0058",
      "name": "NO_NAME",
      "missing_fields": [
        "class",
        "name"
      ]
    },
    {
      "id": "kg_Example_0059",
      "name": "% create_design_definition -name sub \\n    -verilogs /home/user/date/sub.v -def /home/user/date/sub.def",
      "missing_fields": [
        "scenarios"
      ]
    },
    {
      "id": "kg_Example_0060",
      "name": "% create_design_definition -name sub2 \n    -verilogs /home/user/date/sub2.v -def /home/user/date/sub2.def\n% create_design_definition -name top  \n    -verilogs /home/user/date/top.v -def /home/user/date/top.def",
      "missing_fields": [
        "scenarios"
      ]
    },
    {
      "id": "kg_Example_0061",
      "name": "% create_scenario func_worst -corner worst -mode func -temperature 105",
      "missing_fields": [
        "usage",
        "scenarios"
      ]
    },
    {
      "id": "kg_Example_0062",
      "name": "% create_workspace /home/user/tutorial",
      "missing_fields": [
        "scenarios"
      ]
    },
    {
      "id": "kg_Example_0065",
      "name": "% report_fail_reasons -pins \n    [get_critical_gba_path -to st_reg_2_/D -delay_type min \n     -scenario func_fast]",
      "missing_fields": [
        "scenarios"
      ]
    },
    {
      "id": "kg_Example_0066",
      "name": "% get_dont_touch_cells -regex {U[0-9]{2}}",
      "missing_fields": [
        "scenarios"
      ]
    },
    {
      "id": "kg_Example_0068",
      "name": "% get_io_path_pins",
      "missing_fields": [
        "scenarios"
      ]
    },
    {
      "id": "kg_Example_0070",
      "name": "% get_reference_corner\nworst",
      "missing_fields": [
        "usage",
        "scenarios"
      ]
    },
    {
      "id": "kg_Example_0073",
      "name": "% import_power_domain -design TOP \n    -upf_file {/home/user/design/data/test.upf} \n    -region_file {/home/user/design/data/top.pd}",
      "missing_fields": [
        "scenarios"
      ]
    },
    {
      "id": "kg_Example_0077",
      "name": "% define_designs -verilogs $top_verilog_files -defs $top_def_files",
      "missing_fields": [
        "scenarios"
      ]
    },
    {
      "id": "kg_Example_0078",
      "name": "% link_reference_library -format lef /home/user/data/slow.lef",
      "missing_fields": [
        "scenarios"
      ]
    },
    {
      "id": "kg_Example_0079",
      "name": "% link_reference_library -force -format lef /home/user/data/tech.lef",
      "missing_fields": [
        "scenarios"
      ]
    },
    {
      "id": "kg_Example_0081",
      "name": "% purge_specific_lib_cells",
      "missing_fields": [
        "scenarios"
      ]
    },
    {
      "id": "kg_Example_0083",
      "name": "%read_timing_report -pretend -scenario test_slow {1.rpt.gz  2.rpt.gz}%read_timing_report -pretend -scenario func_slow {3.rpt.gz}%read_timing_report          -scenario func_slow {4.rpt.gz}",
      "missing_fields": [
        "scenarios"
      ]
    },
    {
      "id": "kg_Example_0084",
      "name": "% reduce_scenario $sces",
      "missing_fields": [
        "scenarios"
      ]
    },
    {
      "id": "kg_Example_0087",
      "name": "% report_design_info",
      "missing_fields": [
        "scenarios"
      ]
    },
    {
      "id": "kg_Example_0088",
      "name": "NO_NAME",
      "missing_fields": [
        "class",
        "name"
      ]
    },
    {
      "id": "kg_Example_0090",
      "name": "% report_power_domain -design TOP",
      "missing_fields": [
        "scenarios"
      ]
    },
    {
      "id": "kg_Example_0092",
      "name": "% set_removable_fillers {FILLX2 FILLX4 BUFX2 INVX4}\nSet 4 cells as removable.\n% report_removable_fillers",
      "missing_fields": [
        "scenarios"
      ]
    },
    {
      "id": "kg_Example_0093",
      "name": "% set_dont_touch [get_cells \"U4\"]\n% save_user_dont_touch\n% set_dont_touch [get_cells \"U5\"]\n% optimize_leakage_power\n% restore_user_dont_touch",
      "missing_fields": [
        "scenarios"
      ]
    },
    {
      "id": "kg_Example_0095",
      "name": "% set_hier_path_dont_touch alu/add_67",
      "missing_fields": [
        "scenarios"
      ]
    },
    {
      "id": "kg_Example_0096",
      "name": "% set_hier_path_dont_touch alu/add_67 0",
      "missing_fields": [
        "scenarios"
      ]
    },
    {
      "id": "kg_Example_0100",
      "name": "% set_placement_constraint -design B_CORE -max_density 0.5 \n                           -density_region {(80, 80) (100, 100)}",
      "missing_fields": [
        "scenarios"
      ]
    },
    {
      "id": "kg_Example_0101",
      "name": "% set_placement_spacing_label -name DEL3B_R \n    -side right -ref_cells [get_ref_cells DEL3B*]",
      "missing_fields": [
        "scenarios"
      ]
    },
    {
      "id": "kg_Example_0102",
      "name": "% set_placement_spacing_label -name DEL3B_Side \n    -side both -ref_cells [get_ref_cells DEL3B*]",
      "missing_fields": [
        "usage",
        "scenarios"
      ]
    },
    {
      "id": "kg_Example_0105",
      "name": "% set_units -time ps -resistance ohm",
      "missing_fields": [
        "scenarios"
      ]
    },
    {
      "id": "kg_Example_0106",
      "name": "% exchange_cell -design {cpu} regs/dram1/U180/add_buf_1 \n            {regs/dram1/U181/add_buf_2 regs/dram1/U181/add_buf_3}",
      "missing_fields": [
        "scenarios"
      ]
    },
    {
      "id": "kg_Example_0107",
      "name": "% insert_buffer -design {regs} {dram1/C3/U574/C1} {BUFFD6 BUFFD6}",
      "missing_fields": [
        "scenarios"
      ]
    },
    {
      "id": "kg_Example_0108",
      "name": "% insert_buffer -design {regs} {dram1/C3/U574/C1} {BUFFD12} \n                -locations {(45.247, 57.306)}",
      "missing_fields": [
        "scenarios"
      ]
    },
    {
      "id": "kg_Example_0109",
      "name": "% insert_dummy_cell -design {regs} {dram0/U12/A1} {BUFFD2} \n                    -location {(30.200, 62.870)}",
      "missing_fields": [
        "scenarios"
      ]
    },
    {
      "id": "kg_Example_0110",
      "name": "% list_insert_buffer_candidates -design {cpu} U318/I -inverter -dont_use",
      "missing_fields": [
        "scenarios"
      ]
    },
    {
      "id": "kg_Example_0111",
      "name": "% report_eco_actions -last_n 10 -types size_cell \n                      -top_n 7 -sort_by area",
      "missing_fields": [
        "scenarios"
      ]
    },
    {
      "id": "kg_Example_0112",
      "name": "% report_matched_cells -by_attribute IOA21X4THVT",
      "missing_fields": [
        "scenarios"
      ]
    },
    {
      "id": "kg_Example_0116",
      "name": "% summarize_capacitance_violations -with_reference -with_delta \n                                   -data_path",
      "missing_fields": [
        "scenarios"
      ]
    },
    {
      "id": "kg_Example_0117",
      "name": "% summarize_fanout_violations -data_path",
      "missing_fields": [
        "scenarios"
      ]
    },
    {
      "id": "kg_Example_0120",
      "name": "% summarize_inst_displacement [get_cells -hierarchical U41*]",
      "missing_fields": [
        "scenarios"
      ]
    },
    {
      "id": "kg_Example_0121",
      "name": "% summarize_inst_displacement -recursive -include_location -with_distribution",
      "missing_fields": [
        "scenarios"
      ]
    },
    {
      "id": "kg_Example_0122",
      "name": "% summarize_leakage_power -keywords {ULVT LVT \"\" HVT}",
      "missing_fields": [
        "scenarios"
      ]
    },
    {
      "id": "kg_Example_0123",
      "name": "% summarize_path_violations -with_top_n 3",
      "missing_fields": [
        "scenarios"
      ]
    },
    {
      "id": "kg_Example_0124",
      "name": "% write_design_changes -eco_file_prefix inno_atomic \n                       -format INNOVUS  -write_atomic_cmd",
      "missing_fields": [
        "scenarios"
      ]
    },
    {
      "id": "kg_Example_0125",
      "name": "% write_design_changes -eco_file_prefix inno_macro -last_n 5 \n                       -format INNOVUS ",
      "missing_fields": [
        "scenarios"
      ]
    },
    {
      "id": "kg_Example_0126",
      "name": "% write_design_changes -eco_file_prefix inno_macro \\n                       -format INNOVUS -force",
      "missing_fields": [
        "scenarios"
      ]
    },
    {
      "id": "kg_Example_0128",
      "name": "% analyze_leakage_keywords -group 3",
      "missing_fields": [
        "scenarios"
      ]
    },
    {
      "id": "kg_Example_0129",
      "name": "% clock_eco_analysis -buffer BUFF12 -hold",
      "missing_fields": [
        "scenarios"
      ]
    },
    {
      "id": "kg_Example_0130",
      "name": "% commit_clock_eco -hold -top 10",
      "missing_fields": [
        "scenarios"
      ]
    },
    {
      "id": "kg_Example_0131",
      "name": "% enlarge_timing_violations -hold 1.1",
      "missing_fields": [
        "scenarios"
      ]
    },
    {
      "id": "kg_Example_0133",
      "name": "% fix_capacitance_violations -on_clock",
      "missing_fields": [
        "scenarios"
      ]
    },
    {
      "id": "kg_Example_0134",
      "name": "% fix_capacitance_violations -capacitance_target 0.02",
      "missing_fields": [
        "scenarios"
      ]
    },
    {
      "id": "kg_Example_0135",
      "name": "% fix_capacitance_violations -transition_margin 0.01 \n                             -capacitance_margin 0.01",
      "missing_fields": [
        "scenarios"
      ]
    },
    {
      "id": "kg_Example_0137",
      "name": "% fix_fanout_violations {mul137/ZN}",
      "missing_fields": [
        "scenarios"
      ]
    },
    {
      "id": "kg_Example_0139",
      "name": "% fix_hold_path_violations -effort high",
      "missing_fields": [
        "scenarios"
      ]
    },
    {
      "id": "kg_Example_0140",
      "name": "% set_parameter eco_hold_slack_target 0.005\n% set_parameter eco_setup_slack_margin 0.005\n% fix_hold_path_violations -setup_margin 0.01 -hold_target 0",
      "missing_fields": [
        "scenarios"
      ]
    },
    {
      "id": "kg_Example_0141",
      "name": "% fix_hold_path_violations [get_paths -delay_type min \n                           -lower_bound -1.000 -upper_bound 0.000]",
      "missing_fields": [
        "scenarios"
      ]
    },
    {
      "id": "kg_Example_0142",
      "name": "% fix_hold_path_violations -buffer_list \"DLY01 DLY02 DLY04\"                            -max_cluster_loader_count 3",
      "missing_fields": [
        "scenarios"
      ]
    },
    {
      "id": "kg_Example_0143",
      "name": "% set_parameter eco_dummy_cell_list_for_hold {BUF02}\n% fix_hold_path_violations -use_dummy_cell -dummy_only",
      "missing_fields": [
        "scenarios"
      ]
    },
    {
      "id": "kg_Example_0146",
      "name": "% fix_setup_path_violations -methods \"size_cell\"",
      "missing_fields": [
        "scenarios"
      ]
    },
    {
      "id": "kg_Example_0147",
      "name": "% set_parameter eco_setup_slack_target 0.005\n% set_parameter eco_hold_slack_margin -0.005\n% fix_setup_path_violations",
      "missing_fields": [
        "usage",
        "scenarios"
      ]
    },
    {
      "id": "kg_Example_0151",
      "name": "% fix_transition_violations -on_clock",
      "missing_fields": [
        "scenarios"
      ]
    },
    {
      "id": "kg_Example_0152",
      "name": "% fix_transition_violations -transition_target 0.02",
      "missing_fields": [
        "scenarios"
      ]
    },
    {
      "id": "kg_Example_0154",
      "name": "% fix_violations_by_clock_eco -buffer CKBUFF1 -hold",
      "missing_fields": [
        "scenarios"
      ]
    },
    {
      "id": "kg_Example_0155",
      "name": "% fix_violations_by_clock_eco -buffer CKBUFF1 -setup  -trace_level 4",
      "missing_fields": [
        "scenarios"
      ]
    },
    {
      "id": "kg_Example_0156",
      "name": "% fix_wire_length_violations -buffer_list {BUF01 BUF0} -on_clock",
      "missing_fields": [
        "scenarios"
      ]
    },
    {
      "id": "kg_Example_0157",
      "name": "% mark_area_pin_rank -type margin",
      "missing_fields": [
        "scenarios"
      ]
    },
    {
      "id": "kg_Example_0158",
      "name": "% mark_setup_gba_pin_rank -type margin",
      "missing_fields": [
        "scenarios"
      ]
    },
    {
      "id": "kg_Example_0159",
      "name": "% set_parameter eco_cell_nominal_sizing_pattern {X([0-9]+)TH}\n% optimize_design_area -setup_margin 0.01 -transition_margin 0.05",
      "missing_fields": [
        "scenarios"
      ]
    },
    {
      "id": "kg_Example_0160",
      "name": "% optimize_design_area [get_cells_in_region -rect \"((0.0, 0.0)(11.0, 95.0))\"]",
      "missing_fields": [
        "scenarios"
      ]
    },
    {
      "id": "kg_Example_0162",
      "name": "% optimize_leakage_power -keywords {\"10ULVT\" \"10LVT\" \"20ULVT\" \"20LVT\"} -auto_iteration 3",
      "missing_fields": [
        "scenarios"
      ]
    },
    {
      "id": "kg_Example_0163",
      "name": "NO_NAME",
      "missing_fields": [
        "class",
        "name"
      ]
    },
    {
      "id": "kg_Example_0164",
      "name": "% report_fail_reasons -pins * -stats Reason                                                   Count   % ------------------------------------------------------------------- break_setup_of_driver  ################################    49 79.0% break_setup            #####...........................     7 11.3% break_max_capacitance  ####............................     6  9.7% ",
      "missing_fields": [
        "scenarios"
      ]
    },
    {
      "id": "kg_Example_0165",
      "name": "% report_fail_reasons -methods size_cell -pins * -disable_timing",
      "missing_fields": [
        "scenarios"
      ]
    },
    {
      "id": "kg_Example_0166",
      "name": "% summarize_buffers [get_lib_cells */BUFFD*]",
      "missing_fields": [
        "scenarios"
      ]
    },
    {
      "id": "kg_Example_0167",
      "name": "% summarize_pin_rank",
      "missing_fields": [
        "scenarios"
      ]
    },
    {
      "id": "kg_Example_0168",
      "name": "write_incremental_sdf -dir dir_to_save -hold -target 0.02",
      "missing_fields": [
        "scenarios"
      ]
    },
    {
      "id": "kg_Example_0173",
      "name": "% set_parameter tmlib_constraint_calculate_method {setup_only}",
      "missing_fields": [
        "scenarios"
      ]
    },
    {
      "id": "kg_Example_0176",
      "name": "set_parameter tmlib_sequential_delay_definition {constraint_window}",
      "missing_fields": [
        "scenarios"
      ]
    },
    {
      "id": "kg_Example_0186",
      "name": "set_parameter eco_cell_classify_rule nominal_regex\nset_parameter eco_cell_nominal_sizing_pattern {X([0-9]+)TH}",
      "missing_fields": [
        "scenarios"
      ]
    },
    {
      "id": "kg_Example_0193",
      "name": "set_parameter eco_post_mask_mode true\nset_parameter eco_ga_name_patterns {GAFILL* GBUFF*}\nset_parameter eco_ga_filler_list {GAFILLER1 GAFILLER2}\nset_parameter eco_buffer_list_for_hold  {GBUFFD1BWP12T GBUFFD3BWP12T}\nset_parameter eco_buffer_list_for_setup {GBUFFD1BWP12T GBUFFD3BWP12T}\nfix_setup/hold_gba_violations ...",
      "missing_fields": [
        "scenarios"
      ]
    },
    {
      "id": "kg_Example_0198",
      "name": "% set_parameter eco_skip_unconstrained_cell_rule all",
      "missing_fields": [
        "scenarios"
      ]
    },
    {
      "id": "kg_Example_0200",
      "name": "xtop> create_design_definition-name B -verilogs b.v",
      "missing_fields": [
        "scenarios"
      ]
    },
    {
      "id": "kg_Example_0201",
      "name": "xtop> import_designs",
      "missing_fields": [
        "scenarios"
      ]
    },
    {
      "id": "kg_Example_0202",
      "name": "xtop > report_tech_group",
      "missing_fields": [
        "scenarios"
      ]
    },
    {
      "id": "kg_Example_0203",
      "name": "xtop > get_tech_group -design cpu",
      "missing_fields": [
        "scenarios"
      ]
    },
    {
      "id": "kg_Example_0204",
      "name": "xtop> set_skip_scenario test_slow",
      "missing_fields": [
        "scenarios"
      ]
    },
    {
      "id": "kg_Example_0205",
      "name": "xtop> set_placement_constraint -design B_CORE -max_density 0.6 -density_region {(0, 0, 30, 30)}",
      "missing_fields": [
        "scenarios"
      ]
    },
    {
      "id": "kg_Example_0206",
      "name": "xtop > set_specific_lib_cells -design cpu -recursive  SP*",
      "missing_fields": [
        "scenarios"
      ]
    },
    {
      "id": "kg_Example_0207",
      "name": "NO_NAME",
      "missing_fields": [
        "class",
        "name",
        "scenarios"
      ]
    },
    {
      "id": "kg_Example_0210",
      "name": "xtop > fix_transition/capacitance/fanout/si/wire_length_violations ...  -debug_pins ...",
      "missing_fields": [
        "scenarios"
      ]
    },
    {
      "id": "kg_Example_0211",
      "name": "xtop > optimiza_leakage_power/design_area ...  -debug_pins ...",
      "missing_fields": [
        "scenarios"
      ]
    },
    {
      "id": "kg_Example_0215",
      "name": "xtop > set_placement_spacing_label -name normal_top -vertical_side top -ref_cells {get_ref_cells *}",
      "missing_fields": [
        "usage",
        "scenarios"
      ]
    },
    {
      "id": "kg_Example_0219",
      "name": "NO_NAME",
      "missing_fields": [
        "class",
        "name",
        "usage"
      ]
    },
    {
      "id": "kg_Example_0220",
      "name": "pr_shell> source .../dump_power_domain_from_xxx.tcl\npr_shell> write_pd_for_xtop dirName",
      "missing_fields": [
        "scenarios"
      ]
    },
    {
      "id": "kg_Example_0221",
      "name": "sta_shell> report_pba_data_for_icexplorer -scenario_name func_fast -dir sta_data \\-delay_type min_max -max_paths 10000 -nworst 10",
      "missing_fields": [
        "scenarios"
      ]
    },
    {
      "id": "kg_Example_0223",
      "name": "link_reference_library -format lef \"./tech.lef ./tech.par.lef ./std.lef ./ip.lef ...\"",
      "missing_fields": [
        "scenarios"
      ]
    },
    {
      "id": "kg_Example_0224",
      "name": "import_designs",
      "missing_fields": [
        "scenarios"
      ]
    },
    {
      "id": "kg_Example_0225",
      "name": "import_power_domain -design cpu -upf ../pd/cpu.upf} -region ../pd/cpu.pd)",
      "missing_fields": [
        "scenarios"
      ]
    },
    {
      "id": "kg_Example_0226",
      "name": "set_parameter eco_buffer_list_for_setup {BUF2 BUF4 BUF6}",
      "missing_fields": [
        "scenarios"
      ]
    },
    {
      "id": "kg_Example_0227",
      "name": "set_parameter eco_max_buffer_chain_length 8",
      "missing_fields": [
        "usage",
        "scenarios"
      ]
    },
    {
      "id": "kg_Example_0228",
      "name": "set_parameter eco_cell_nominal_sizing_pattern {D{0-9}+BWP}",
      "missing_fields": [
        "usage",
        "scenarios"
      ]
    },
    {
      "id": "kg_Example_0231",
      "name": "#set_hier_path_dont_touch {hier_path1 hier_path2} true",
      "missing_fields": [
        "scenarios"
      ]
    },
    {
      "id": "kg_Example_0232",
      "name": "#set_module_dont_touch {module1 module2} true",
      "missing_fields": [
        "scenarios"
      ]
    },
    {
      "id": "kg_Example_0234",
      "name": "#set_module_dont_touch {sub_module1 sub_module2} false",
      "missing_fields": [
        "scenarios"
      ]
    },
    {
      "id": "kg_Example_0235",
      "name": "#set_lib_per_instance {regs/draml/C3} {tutorialbc.idb} -corner fast",
      "missing_fields": [
        "usage",
        "scenarios"
      ]
    },
    {
      "id": "kg_Example_0236",
      "name": "write_design_changes -format <PR> -eco_file_prefix xtop_opt_<PR> -output_dir $eco_output_dir",
      "missing_fields": [
        "scenarios"
      ]
    },
    {
      "id": "kg_Example_0238",
      "name": "xtop > set_parameter eco_cell_nominal_swap_keywords {lvt@n30 nvt@n40 hvt@n40}",
      "missing_fields": [
        "usage",
        "scenarios"
      ]
    },
    {
      "id": "kg_Example_0239",
      "name": "xtop > fix_setup_path/gba_violations -buffer_list {BUFX2 BUFX4 ...} -setup_target 0.0 -hold_margin 0.0",
      "missing_fields": [
        "scenarios"
      ]
    },
    {
      "id": "kg_Example_0240",
      "name": "NO_NAME",
      "missing_fields": [
        "class",
        "name"
      ]
    },
    {
      "id": "kg_Example_0241",
      "name": "NO_NAME",
      "missing_fields": [
        "class",
        "name"
      ]
    },
    {
      "id": "kg_Example_0243",
      "name": "NO_NAME",
      "missing_fields": [
        "class",
        "name"
      ]
    },
    {
      "id": "kg_Example_0244",
      "name": "NO_NAME",
      "missing_fields": [
        "class",
        "name"
      ]
    },
    {
      "id": "kg_Example_0245",
      "name": "xtop > fix_glitch_violations -buffer BUF01",
      "missing_fields": [
        "scenarios"
      ]
    },
    {
      "id": "kg_Example_0246",
      "name": "p*_tool > source $ICEEXPLORER_XTOP_HOME/utilities/sta/pt_util2.tcl\np*_tool > report_scenario_data_for_iceplorer ...\n-dumpVoltageData //Or, voltage info can be read from timing library file\n-dump_toggle_rate //Or, toggle rate can be specified by eco_power_toggle_rate",
      "missing_fields": [
        "scenarios"
      ]
    },
    {
      "id": "kg_Example_0247",
      "name": "xtop > read_timing_data ... //read in toggle_rate/rail_voltage information",
      "missing_fields": [
        "usage",
        "scenarios"
      ]
    },
    {
      "id": "kg_Example_0248",
      "name": "xtop > summarize_dynamic_power -as_reference",
      "missing_fields": [
        "usage",
        "scenarios"
      ]
    },
    {
      "id": "kg_Example_0250",
      "name": "xtop > optimize_dynamic_power",
      "missing_fields": [
        "scenarios"
      ]
    },
    {
      "id": "kg_Example_0251",
      "name": "xtop > summarize_dynamic_power -with_reference",
      "missing_fields": [
        "scenarios"
      ]
    },
    {
      "id": "kg_Example_0252",
      "name": "xtop > optimize_design_area -remove_buffer_only",
      "missing_fields": [
        "scenarios"
      ]
    },
    {
      "id": "kg_Example_0253",
      "name": "xtop > set_parameter eco_cell_nominal_sizing_pattern {X([0-9]+)TH}",
      "missing_fields": [
        "scenarios"
      ]
    },
    {
      "id": "kg_Example_0254",
      "name": "xtop > build_timing_graph\nxtop > analyze_scenario_reduction -hold_top_n 2 -data_dir timing_data_dir -verbose",
      "missing_fields": [
        "scenarios"
      ]
    },
    {
      "id": "kg_Example_0255",
      "name": "xtop> exchange_cell -design {cpu} { U333 } { U357 }",
      "missing_fields": [
        "scenarios"
      ]
    },
    {
      "id": "kg_Example_0257",
      "name": "xtop > summarize_path_violations [get_paths -delay_type max ]",
      "missing_fields": [
        "scenarios"
      ]
    },
    {
      "id": "kg_Example_0258",
      "name": "xtop > summarize_gba_violations -hold -with_reference",
      "missing_fields": [
        "scenarios"
      ]
    },
    {
      "id": "kg_Example_0259",
      "name": "xtop > summarize_capacitance_violations -data_path",
      "missing_fields": [
        "usage",
        "scenarios"
      ]
    },
    {
      "id": "kg_Example_0260",
      "name": "NO_NAME",
      "missing_fields": [
        "class",
        "name"
      ]
    },
    {
      "id": "kg_Example_0261",
      "name": "xtop > summarize_dynamic_power -hier_path_list {A1 A1/B3 A1/B3/C2}",
      "missing_fields": [
        "scenarios"
      ]
    },
    {
      "id": "kg_Example_0265",
      "name": "xtop > get_failed_pins -reasons fail_to_legalize",
      "missing_fields": [
        "scenarios"
      ]
    },
    {
      "id": "kg_Example_0266",
      "name": "xtpo> set_parameter eco_buffer_list_for_setup/hold {AN2 OR2 BUF2}",
      "missing_fields": [
        "usage",
        "scenarios"
      ]
    },
    {
      "id": "kg_Example_0267",
      "name": "xtop > set_parameter eco_cell_nominal_swap_keywords {HVT@ @P55 HVT@P55 }",
      "missing_fields": [
        "usage",
        "scenarios"
      ]
    },
    {
      "id": "kg_Example_0268",
      "name": "xtop > set_placement_spacing_label -name DEL3B_R -side right -ref_cells [get_ref_cells */DEL3B*]",
      "missing_fields": [
        "scenarios"
      ]
    },
    {
      "id": "kg_Example_0270",
      "name": "xtop > fix_hold_gba_violations ... -size_cell_only",
      "missing_fields": [
        "usage",
        "scenarios"
      ]
    },
    {
      "id": "kg_Example_0271",
      "name": "xtop > set_parameter eco_setup_slack_target 0 ;#The unit is ns",
      "missing_fields": [
        "scenarios"
      ]
    },
    {
      "id": "kg_Example_0273",
      "name": "xtop > set_hier_path_dont_touch alu/add_67 false",
      "missing_fields": [
        "scenarios"
      ]
    },
    {
      "id": "kg_Example_0274",
      "name": "xtop > get_dont_touch_pins -hierarchical -nocase u*/*",
      "missing_fields": [
        "scenarios"
      ]
    },
    {
      "id": "kg_Example_0275",
      "name": "xtop > link_reference_library ...\ntop > set_removable_fillers {FILLX2 FILLX4 DCAPX8 DCAPX12}\ntop > set_parameter defin_skip_removable_fillers true\ntop > set_parameter defin_skip_pg_layers_mode {UPPER} # ignore P/G net shapes,\ntop > import_designs # above the first P/G vertical layer",
      "missing_fields": [
        "scenarios"
      ]
    }
  ]
}